{
    "Liga": "3. Liga",
    "Spieltag": "1",
    "0": {
        "Tabellenplatz": "1",
        "Teamname": "FC Ingolstadt ",
        "Spiel": "1",
        "Tore": "2:0",
        "Tordifferenz": "2",
        "Punkte": "3"
    },
    "1": {
        "Tabellenplatz": "2",
        "Teamname": "Regensburg",
        "Spiel": "1",
        "Tore": "2:0",
        "Tordifferenz": "2",
        "Punkte": "3"
    },
    "2": {
        "Tabellenplatz": "3",
        "Teamname": "Burghausen",
        "Spiel": "1",
        "Tore": "4:3",
        "Tordifferenz": "1",
        "Punkte": "3"
    },
    "3": {
        "Tabellenplatz": "4",
        "Teamname": "FC Carl Zeiss ",
        "Spiel": "1",
        "Tore": "2:1",
        "Tordifferenz": "1",
        "Punkte": "3"
    },
    "4": {
        "Tabellenplatz": "5",
        "Teamname": "Braunschweig",
        "Spiel": "1",
        "Tore": "1:0",
        "Tordifferenz": "1",
        "Punkte": "3"
    },
    "5": {
        "Tabellenplatz": "6",
        "Teamname": "Stuttgart II",
        "Spiel": "1",
        "Tore": "1:0",
        "Tordifferenz": "1",
        "Punkte": "3"
    },
    "6": {
        "Tabellenplatz": "7",
        "Teamname": "Sandhausen",
        "Spiel": "1",
        "Tore": "3:3",
        "Tordifferenz": "0",
        "Punkte": "1"
    },
    "7": {
        "Tabellenplatz": "8",
        "Teamname": "Unterhaching",
        "Spiel": "1",
        "Tore": "3:3",
        "Tordifferenz": "0",
        "Punkte": "1"
    },
    "8": {
        "Tabellenplatz": "9",
        "Teamname": "Heidenheim",
        "Spiel": "1",
        "Tore": "2:2",
        "Tordifferenz": "0",
        "Punkte": "1"
    },
    "9": {
        "Tabellenplatz": "10",
        "Teamname": "Wuppertal",
        "Spiel": "1",
        "Tore": "2:2",
        "Tordifferenz": "0",
        "Punkte": "1"
    },
    "10": {
        "Tabellenplatz": "11",
        "Teamname": "Offenbach",
        "Spiel": "1",
        "Tore": "0:0",
        "Tordifferenz": "0",
        "Punkte": "1"
    },
    "11": {
        "Tabellenplatz": "12",
        "Teamname": "RW Erfurt",
        "Spiel": "1",
        "Tore": "0:0",
        "Tordifferenz": "0",
        "Punkte": "1"
    },
    "12": {
        "Tabellenplatz": "13",
        "Teamname": "Bremen II",
        "Spiel": "1",
        "Tore": "0:0",
        "Tordifferenz": "0",
        "Punkte": "1"
    },
    "13": {
        "Tabellenplatz": "14",
        "Teamname": "Aue",
        "Spiel": "1",
        "Tore": "0:0",
        "Tordifferenz": "0",
        "Punkte": "1"
    },
    "14": {
        "Tabellenplatz": "15",
        "Teamname": "Dortmund II",
        "Spiel": "1",
        "Tore": "3:4",
        "Tordifferenz": "-1",
        "Punkte": "0"
    },
    "15": {
        "Tabellenplatz": "16",
        "Teamname": "Wehen",
        "Spiel": "1",
        "Tore": "1:2",
        "Tordifferenz": "-1",
        "Punkte": "0"
    },
    "16": {
        "Tabellenplatz": "17",
        "Teamname": "Osnabrück",
        "Spiel": "1",
        "Tore": "0:1",
        "Tordifferenz": "-1",
        "Punkte": "0"
    },
    "17": {
        "Tabellenplatz": "18",
        "Teamname": "Dresden",
        "Spiel": "1",
        "Tore": "0:1",
        "Tordifferenz": "-1",
        "Punkte": "0"
    },
    "18": {
        "Tabellenplatz": "19",
        "Teamname": "FC Bayern II",
        "Spiel": "1",
        "Tore": "0:2",
        "Tordifferenz": "-2",
        "Punkte": "0"
    },
    "19": {
        "Tabellenplatz": "20",
        "Teamname": "Holstein Kiel",
        "Spiel": "1",
        "Tore": "0:2",
        "Tordifferenz": "-2",
        "Punkte": "0"
    }
}