{
    "0": {
        "Teamname": "SV Babelsberg 03",
        "Platz": "1",
        "Spiele": "2",
        "Gewonnen": "2",
        "Unentschieden": "0",
        "Verloren": "0",
        "Tore": "5:2",
        "Tordifferenz": "3",
        "Punkte": "6"
    },
    "1": {
        "Teamname": "VSG Altglienicke",
        "Platz": "2",
        "Spiele": "2",
        "Gewonnen": "2",
        "Unentschieden": "0",
        "Verloren": "0",
        "Tore": "4:1",
        "Tordifferenz": "3",
        "Punkte": "6"
    },
    "2": {
        "Teamname": "Berliner AK",
        "Platz": "3",
        "Spiele": "2",
        "Gewonnen": "2",
        "Unentschieden": "0",
        "Verloren": "0",
        "Tore": "3:0",
        "Tordifferenz": "3",
        "Punkte": "6"
    },
    "3": {
        "Teamname": "FC Carl Zeiss Jena",
        "Platz": "4",
        "Spiele": "2",
        "Gewonnen": "1",
        "Unentschieden": "1",
        "Verloren": "0",
        "Tore": "7:1",
        "Tordifferenz": "6",
        "Punkte": "4"
    },
    "4": {
        "Teamname": "FC Rot-Weiß Erfurt",
        "Platz": "5",
        "Spiele": "2",
        "Gewonnen": "1",
        "Unentschieden": "1",
        "Verloren": "0",
        "Tore": "6:1",
        "Tordifferenz": "5",
        "Punkte": "4"
    },
    "5": {
        "Teamname": "Chemnitzer FC",
        "Platz": "6",
        "Spiele": "2",
        "Gewonnen": "1",
        "Unentschieden": "1",
        "Verloren": "0",
        "Tore": "3:0",
        "Tordifferenz": "3",
        "Punkte": "4"
    },
    "6": {
        "Teamname": "1. FC Lok Leipzig",
        "Platz": "7",
        "Spiele": "2",
        "Gewonnen": "1",
        "Unentschieden": "1",
        "Verloren": "0",
        "Tore": "6:4",
        "Tordifferenz": "2",
        "Punkte": "4"
    },
    "7": {
        "Teamname": "ZFC Meuselwitz",
        "Platz": "8",
        "Spiele": "2",
        "Gewonnen": "1",
        "Unentschieden": "0",
        "Verloren": "1",
        "Tore": "4:2",
        "Tordifferenz": "2",
        "Punkte": "3"
    },
    "8": {
        "Teamname": "FC Energie Cottbus",
        "Platz": "9",
        "Spiele": "2",
        "Gewonnen": "1",
        "Unentschieden": "0",
        "Verloren": "1",
        "Tore": "3:2",
        "Tordifferenz": "1",
        "Punkte": "3"
    },
    "9": {
        "Teamname": "BFC Dynamo",
        "Platz": "10",
        "Spiele": "2",
        "Gewonnen": "1",
        "Unentschieden": "0",
        "Verloren": "1",
        "Tore": "2:2",
        "Tordifferenz": "0",
        "Punkte": "3"
    },
    "10": {
        "Teamname": "SV Lichtenberg 47",
        "Platz": "11",
        "Spiele": "2",
        "Gewonnen": "1",
        "Unentschieden": "0",
        "Verloren": "1",
        "Tore": "2:6",
        "Tordifferenz": "-4",
        "Punkte": "3"
    },
    "11": {
        "Teamname": "FC Viktoria Berlin",
        "Platz": "12",
        "Spiele": "2",
        "Gewonnen": "0",
        "Unentschieden": "2",
        "Verloren": "0",
        "Tore": "3:3",
        "Tordifferenz": "0",
        "Punkte": "2"
    },
    "12": {
        "Teamname": "Greifswalder FC",
        "Platz": "13",
        "Spiele": "2",
        "Gewonnen": "0",
        "Unentschieden": "1",
        "Verloren": "1",
        "Tore": "0:2",
        "Tordifferenz": "-2",
        "Punkte": "1"
    },
    "13": {
        "Teamname": "FSV 63 Luckenwalde",
        "Platz": "14",
        "Spiele": "2",
        "Gewonnen": "0",
        "Unentschieden": "1",
        "Verloren": "1",
        "Tore": "1:4",
        "Tordifferenz": "-3",
        "Punkte": "1"
    },
    "14": {
        "Teamname": "BSG Chemie Leipzig",
        "Platz": "15",
        "Spiele": "2",
        "Gewonnen": "0",
        "Unentschieden": "0",
        "Verloren": "2",
        "Tore": "3:6",
        "Tordifferenz": "-3",
        "Punkte": "0"
    },
    "15": {
        "Teamname": "Hertha BSC II",
        "Platz": "16",
        "Spiele": "2",
        "Gewonnen": "0",
        "Unentschieden": "0",
        "Verloren": "2",
        "Tore": "2:5",
        "Tordifferenz": "-3",
        "Punkte": "0"
    },
    "16": {
        "Teamname": "Germania Halberstadt",
        "Platz": "17",
        "Spiele": "2",
        "Gewonnen": "0",
        "Unentschieden": "0",
        "Verloren": "2",
        "Tore": "1:5",
        "Tordifferenz": "-4",
        "Punkte": "0"
    },
    "17": {
        "Teamname": "Tennis Bor. Berlin",
        "Platz": "18",
        "Spiele": "2",
        "Gewonnen": "0",
        "Unentschieden": "0",
        "Verloren": "2",
        "Tore": "0:9",
        "Tordifferenz": "-9",
        "Punkte": "0"
    }
}