{
    "Liga": "Regionalliga Nord/Ost",
    "Spieltag": "14",
    "0": {
        "Tabellenplatz": "1",
        "Teamname": "Neustrelitz",
        "Spiel": "14",
        "Tore": "29:6",
        "Tordifferenz": "23",
        "Punkte": "37"
    },
    "1": {
        "Tabellenplatz": "2",
        "Teamname": "Union II",
        "Spiel": "14",
        "Tore": "43:23",
        "Tordifferenz": "20",
        "Punkte": "29"
    },
    "2": {
        "Tabellenplatz": "3",
        "Teamname": "FC Carl Zeiss ",
        "Spiel": "14",
        "Tore": "27:14",
        "Tordifferenz": "13",
        "Punkte": "29"
    },
    "3": {
        "Tabellenplatz": "4",
        "Teamname": "Berliner AK 07",
        "Spiel": "14",
        "Tore": "27:13",
        "Tordifferenz": "14",
        "Punkte": "27"
    },
    "4": {
        "Tabellenplatz": "5",
        "Teamname": "Magdeburg",
        "Spiel": "14",
        "Tore": "32:19",
        "Tordifferenz": "13",
        "Punkte": "27"
    },
    "5": {
        "Tabellenplatz": "6",
        "Teamname": "Plauen",
        "Spiel": "14",
        "Tore": "22:23",
        "Tordifferenz": "-1",
        "Punkte": "20"
    },
    "6": {
        "Tabellenplatz": "7",
        "Teamname": "Zwickau",
        "Spiel": "14",
        "Tore": "21:26",
        "Tordifferenz": "-5",
        "Punkte": "20"
    },
    "7": {
        "Tabellenplatz": "8",
        "Teamname": "Halberstadt",
        "Spiel": "14",
        "Tore": "21:33",
        "Tordifferenz": "-12",
        "Punkte": "19"
    },
    "8": {
        "Tabellenplatz": "9",
        "Teamname": "Babelsberg",
        "Spiel": "14",
        "Tore": "24:25",
        "Tordifferenz": "-1",
        "Punkte": "18"
    },
    "9": {
        "Tabellenplatz": "10",
        "Teamname": "Viktoria 89",
        "Spiel": "14",
        "Tore": "17:19",
        "Tordifferenz": "-2",
        "Punkte": "17"
    },
    "10": {
        "Tabellenplatz": "11",
        "Teamname": "Nordhausen",
        "Spiel": "14",
        "Tore": "18:23",
        "Tordifferenz": "-5",
        "Punkte": "14"
    },
    "11": {
        "Tabellenplatz": "12",
        "Teamname": "Auerbach",
        "Spiel": "14",
        "Tore": "16:28",
        "Tordifferenz": "-12",
        "Punkte": "13"
    },
    "12": {
        "Tabellenplatz": "13",
        "Teamname": "Rathenow",
        "Spiel": "14",
        "Tore": "14:23",
        "Tordifferenz": "-9",
        "Punkte": "12"
    },
    "13": {
        "Tabellenplatz": "14",
        "Teamname": "Meuselwitz",
        "Spiel": "14",
        "Tore": "12:25",
        "Tordifferenz": "-13",
        "Punkte": "12"
    },
    "14": {
        "Tabellenplatz": "15",
        "Teamname": "HBSC II",
        "Spiel": "14",
        "Tore": "17:28",
        "Tordifferenz": "-11",
        "Punkte": "9"
    },
    "15": {
        "Tabellenplatz": "16",
        "Teamname": "Lok Leipzig",
        "Spiel": "14",
        "Tore": "11:23",
        "Tordifferenz": "-12",
        "Punkte": "8"
    }
}