{
    "Liga": "3. Liga",
    "Spieltag": "15",
    "0": {
        "Heimteam": "Unterhaching",
        "Gastteam": "K'lautern",
        "Datum": "Freitag, 11.12.2020",
        "Endergebnis": "2:0",
        "Pausenergebnis": "0:0"
    },
    "1": {
        "Heimteam": "Uerdingen",
        "Gastteam": "Türkgücü",
        "Datum": "Samstag, 12.12.2020",
        "Endergebnis": "1:0",
        "Pausenergebnis": "1:0"
    },
    "2": {
        "Heimteam": "Duisburg",
        "Gastteam": "Wehen",
        "Datum": "Samstag, 12.12.2020",
        "Endergebnis": "4:1",
        "Pausenergebnis": "1:0"
    },
    "3": {
        "Heimteam": "TSV 1860",
        "Gastteam": "Mannheim",
        "Datum": "Samstag, 12.12.2020",
        "Endergebnis": "5:0",
        "Pausenergebnis": "3:0"
    },
    "4": {
        "Heimteam": "Halle",
        "Gastteam": "Dresden",
        "Datum": "Samstag, 12.12.2020",
        "Endergebnis": "1:3",
        "Pausenergebnis": "1:2"
    },
    "5": {
        "Heimteam": "Verl",
        "Gastteam": "V. Köln",
        "Datum": "Samstag, 12.12.2020",
        "Endergebnis": "1:1",
        "Pausenergebnis": "1:1"
    },
    "6": {
        "Heimteam": "Lübeck",
        "Gastteam": "Magdeburg",
        "Datum": "Samstag, 12.12.2020",
        "Endergebnis": "1:1",
        "Pausenergebnis": "1:1"
    },
    "7": {
        "Heimteam": "Saarbrücken",
        "Gastteam": "FC Bayern II",
        "Datum": "Sonntag, 13.12.2020",
        "Endergebnis": "1:2",
        "Pausenergebnis": "1:2"
    },
    "8": {
        "Heimteam": "Rostock",
        "Gastteam": "Meppen",
        "Datum": "Sonntag, 13.12.2020",
        "Endergebnis": "0:2",
        "Pausenergebnis": "0:1"
    },
    "9": {
        "Heimteam": "Zwickau",
        "Gastteam": "FC Ingolstadt ",
        "Datum": "Mittwoch, 13.01.2021",
        "Endergebnis": "0:2",
        "Pausenergebnis": "0:1"
    }
}