{
    "Liga": "Regionalliga Nord/Ost",
    "Spieltag": "18",
    "0": {
        "Heimteam": "Bautzen",
        "Gastteam": "Auerbach",
        "Datum": "Freitag, 16.12.2016",
        "Endergebnis": "1:1",
        "Pausenergebnis": "0:1"
    },
    "1": {
        "Heimteam": "Neustrelitz",
        "Gastteam": "Viktoria 89",
        "Datum": "Freitag, 16.12.2016",
        "Endergebnis": "1:3",
        "Pausenergebnis": "0:1"
    },
    "2": {
        "Heimteam": "Nordhausen",
        "Gastteam": "Babelsberg",
        "Datum": "Freitag, 16.12.2016",
        "Endergebnis": "3:2",
        "Pausenergebnis": "0:1"
    },
    "3": {
        "Heimteam": "Luckenwalde",
        "Gastteam": "Oberlausitz",
        "Datum": "Samstag, 17.12.2016",
        "Endergebnis": "0:1",
        "Pausenergebnis": "0:1"
    },
    "4": {
        "Heimteam": "Berliner AK 07",
        "Gastteam": "Schönberg",
        "Datum": "Sonntag, 18.12.2016",
        "Endergebnis": "2:2",
        "Pausenergebnis": "1:1"
    },
    "5": {
        "Heimteam": "Fürstenwalde",
        "Gastteam": "BFC Dynamo",
        "Datum": "Sonntag, 18.12.2016",
        "Endergebnis": "4:1",
        "Pausenergebnis": "2:0"
    },
    "6": {
        "Heimteam": "HBSC II",
        "Gastteam": "RB Leipzig",
        "Datum": "Sonntag, 18.12.2016",
        "Endergebnis": "1:1",
        "Pausenergebnis": "1:1"
    },
    "7": {
        "Heimteam": "Cottbus",
        "Gastteam": "Lok Leipzig",
        "Datum": "Sonntag, 18.12.2016",
        "Endergebnis": "2:1",
        "Pausenergebnis": "1:0"
    },
    "8": {
        "Heimteam": "FC Carl Zeiss ",
        "Gastteam": "Meuselwitz",
        "Datum": "Samstag, 28.01.2017",
        "Endergebnis": "1:2",
        "Pausenergebnis": "1:1"
    }
}