{
    "Liga": "Regionalliga Nord/Ost",
    "Spieltag": "25",
    "0": {
        "Heimteam": "Viktoria 89",
        "Gastteam": "Lok Leipzig",
        "Datum": "Samstag, 18.03.2017",
        "Endergebnis": "3:3",
        "Pausenergebnis": "2:2"
    },
    "1": {
        "Heimteam": "BFC Dynamo",
        "Gastteam": "Oberlausitz",
        "Datum": "Sonntag, 19.03.2017",
        "Endergebnis": "1:1",
        "Pausenergebnis": "1:1"
    },
    "2": {
        "Heimteam": "Babelsberg",
        "Gastteam": "Neustrelitz",
        "Datum": "Sonntag, 19.03.2017",
        "Endergebnis": "0:0",
        "Pausenergebnis": "0:0"
    },
    "3": {
        "Heimteam": "FC Carl Zeiss ",
        "Gastteam": "HBSC II",
        "Datum": "Sonntag, 19.03.2017",
        "Endergebnis": "2:2",
        "Pausenergebnis": "1:0"
    },
    "4": {
        "Heimteam": "Fürstenwalde",
        "Gastteam": "Berliner AK 07",
        "Datum": "Sonntag, 19.03.2017",
        "Endergebnis": "4:1",
        "Pausenergebnis": "1:0"
    },
    "5": {
        "Heimteam": "Schönberg",
        "Gastteam": "RB Leipzig",
        "Datum": "Sonntag, 19.03.2017",
        "Endergebnis": "1:6",
        "Pausenergebnis": "1:4"
    },
    "6": {
        "Heimteam": "Bautzen",
        "Gastteam": "Cottbus",
        "Datum": "Sonntag, 19.03.2017",
        "Endergebnis": "0:4",
        "Pausenergebnis": "0:4"
    },
    "7": {
        "Heimteam": "Auerbach",
        "Gastteam": "Luckenwalde",
        "Datum": "Sonntag, 19.03.2017",
        "Endergebnis": "1:1",
        "Pausenergebnis": "0:1"
    },
    "8": {
        "Heimteam": "Meuselwitz",
        "Gastteam": "Nordhausen",
        "Datum": "Sonntag, 19.03.2017",
        "Endergebnis": "0:0",
        "Pausenergebnis": "0:0"
    }
}